[
      {
      "Name":"Rap_1970",
      "Miles_per_Gallon":18,
      "Cylinders":8,
      "Displacement":307,
      "Horsepower":130,
      "Weight_in_lbs":3504,
      "Acceleration":12,
      "Year":"1970-01-01",
      "Origin":"USA",
      "Danceability":3.32126,
      "Energy":5.553237,
      "Key":2,
      "Loudness":6.885102",
      "Speechiness":2,
      "Acousticness":9.828588,
      "Instrumentalness":3.347956,
      "Liveness":7.311006,
      "Valence":4.155406,
      "Tempo":7.932788
   },
   {
      "Name":"Rap_1980",
      "Miles_per_Gallon":18,
      "Cylinders":8,
      "Displacement":307,
      "Horsepower":130,
      "Weight_in_lbs":3504,
      "Acceleration":12,
      "Year":"1970-01-01",
      "Origin":"USA",
      "Danceability":10,
      "Energy":2.623006,
      "Key":10,
      "Loudness":4.465781",
      "Speechiness":10,
      "Acousticness":2,
      "Instrumentalness":2,
      "Liveness":8.358186,
      "Valence":4.793853,
      "Tempo":2
   }
]
